{
  "token": "",
  "prefixes": ["wu!"],
  "lang": "en",
  "owners": [""],
  "wiki": {
    "url": "",
    "allowed_roles": [""],
    "blacklisted_users": [],
    "rcgcdw_extension": {
      "enabled": false,
      "channel_ids": [""],
      "mode": "embed",
      "wiki_name": "",
      "block_duration": "2 weeks",
      "emojis": {
        "delete": ["\uD83C\uDDE9"],
        "revert": ["\uD83C\uDDF7"],
        "block": ["\uD83C\uDDE7"]
      }
    },
    "user_map": {
      "enabled": true,
      "": ""
    },
    "credentials": {
      "username": "",
      "password": ""
    }
  }
}